asf_analysis/s1_lidar/compare_s1_lidar.py
asf_analysis/s1_lidar/download_lidar.py
asf_analysis/s1_lidar/make_spicy_ds.py
asf_analysis/s1_lidar/rmse_table.py
asf_analysis/s1_lidar/__pycache__/download_lidar.cpython-312.pyc
asf_analysis/s1_lidar/__pycache__/make_spicy_ds.cpython-312.pyc
asf_analysis/s1_lidar/__pycache__/rmse_table.cpython-312.pyc
asf_analysis/spicy-analysis/src/compare/hans/combo.py
asf_analysis/spicy-analysis/src/compare/old/alps/download_switerland.py
asf_analysis/spicy-analysis/src/compare/old/random_fields/reorder_mc.py
asf_analysis/spicy-analysis/src/compare/old/random_fields/old/tools/vtk2gslib.py
asf_analysis/spicy-analysis/src/data_acquisition/download_lidar.py
asf_analysis/spicy-analysis/src/data_acquisition/make_grouped_stats.py
asf_analysis/spicy-analysis/src/data_acquisition/make_idaho_dataset.py
asf_analysis/spicy-analysis/src/data_acquisition/make_param_stats.py
asf_analysis/spicy-analysis/src/data_acquisition/make_sd_params.py
asf_analysis/spicy-analysis/src/data_acquisition/make_spicy_ds.py
asf_analysis/spicy-analysis/src/data_acquisition/make_wet_banner.py
asf_analysis/spicy-analysis/src/data_acquisition/old_make_param_stats.py
asf_snow/__init__.py
asf_snow/retrieval_sentinel1_snow.py
asf_snow/run_spicy_snow.py
asf_snow/run_spicy_snow_over_large_area.py
asf_snow/sentinel1_RTC.py
asf_snow/sentinel1_snow.py
asf_snow/__pycache__/__init__.cpython-312.pyc
asf_snow/__pycache__/retrieval_sentinel1_snow.cpython-312.pyc
asf_snow/__pycache__/retrieval_snow_depth_sentinel_1c.cpython-312.pyc
asf_snow/__pycache__/sentinel1_snow.cpython-312.pyc
asf_snow/__pycache__/sentinel_1c_snow.cpython-312.pyc
asf_snow/download/forest_cover.py
asf_snow/download/sentinel1.py
asf_snow/download/snow_cover.py
asf_snow/download/__pycache__/forest_cover.cpython-312.pyc
asf_snow/download/__pycache__/sentinel1.cpython-312.pyc
asf_snow/download/__pycache__/snow_cover.cpython-312.pyc
asf_snow/etc/entrypoint.sh
asf_snow/processing/snow_index.py
asfsnow-0.1.4.dist-info/LICENSE
asfsnow-0.1.4.dist-info/METADATA
asfsnow-0.1.4.dist-info/WHEEL
asfsnow-0.1.4.dist-info/top_level.txt
asfsnow-0.1.4.dist-info/RECORD
