Metadata-Version: 2.1
Name: asfsnow
Version: 0.1.4
Summary: Snow depths calculation
Author-email: CRREL Team <jzhu4@alaska.edu>
License: BSD-3-Clause
Project-URL: Homepage, https://github.com/asfadmin/asf-snow.git
Classifier: Intended Audience :: Science/Research
Classifier: License :: OSI Approved :: BSD License
Classifier: Natural Language :: English
Classifier: Operating System :: OS Independent
Classifier: Programming Language :: Python :: 3
Classifier: Programming Language :: Python :: 3.8
Classifier: Programming Language :: Python :: 3.9
Classifier: Programming Language :: Python :: 3.10
Classifier: Programming Language :: Python :: 3.11
Classifier: Programming Language :: Python :: 3.12
Requires-Python: >=3.8
License-File: LICENSE
Requires-Dist: pip ==24.0
Requires-Dist: spicy-snow ==0.2.1
Requires-Dist: shapely ==2.0.4
Requires-Dist: scipy ==1.13.1
Requires-Dist: netcdf4
Requires-Dist: geopandas
Requires-Dist: utm
Requires-Dist: xarray
Requires-Dist: rioxarray
Requires-Dist: xvec
Requires-Dist: geodatasets
Provides-Extra: develop
Requires-Dist: flake8 ; extra == 'develop'
Requires-Dist: flake8-import-order ; extra == 'develop'
Requires-Dist: flake8-blind-except ; extra == 'develop'
Requires-Dist: flake8-builtins ; extra == 'develop'
Requires-Dist: pytest ; extra == 'develop'
Requires-Dist: pytest-cov ; extra == 'develop'
Requires-Dist: pytest-console-scripts ; extra == 'develop'
